[
  {
    "time": "2026-07-14T01:54:51.074Z",
    "available": 378,
    "holding": 0,
    "sold": 344
  },
  {
    "time": "2026-07-14T03:26:35.386Z",
    "available": 374,
    "holding": 3,
    "sold": 345
  },
  {
    "time": "2026-07-14T05:44:50.625Z",
    "available": 370,
    "holding": 0,
    "sold": 352
  },
  {
    "time": "2026-07-14T07:29:19.569Z",
    "available": 368,
    "holding": 0,
    "sold": 354
  },
  {
    "time": "2026-07-14T09:25:56.290Z",
    "available": 364,
    "holding": 0,
    "sold": 358
  },
  {
    "time": "2026-07-14T12:19:52.220Z",
    "available": 362,
    "holding": 0,
    "sold": 360
  },
  {
    "time": "2026-07-14T14:17:52.595Z",
    "available": 360,
    "holding": 0,
    "sold": 362
  },
  {
    "time": "2026-07-14T15:49:49.051Z",
    "available": 358,
    "holding": 0,
    "sold": 364
  },
  {
    "time": "2026-07-14T16:55:30.232Z",
    "available": 354,
    "holding": 0,
    "sold": 368
  },
  {
    "time": "2026-07-15T03:30:28.165Z",
    "available": 352,
    "holding": 0,
    "sold": 370
  },
  {
    "time": "2026-07-15T07:44:43.704Z",
    "available": 350,
    "holding": 0,
    "sold": 372
  },
  {
    "time": "2026-07-15T14:25:45.478Z",
    "available": 348,
    "holding": 0,
    "sold": 374
  },
  {
    "time": "2026-07-16T12:11:28.499Z",
    "available": 347,
    "holding": 0,
    "sold": 375
  },
  {
    "time": "2026-07-17T16:49:24.321Z",
    "available": 344,
    "holding": 0,
    "sold": 378
  },
  {
    "time": "2026-07-17T18:43:52.772Z",
    "available": 343,
    "holding": 1,
    "sold": 378
  }
]